guise/__init__.py
guise/nlp.py
guise/tools.py
guise/util.py
guise/word_clouds.py
guise/word_scoring.py
guise/examples/__init__.py
guise/examples/energy_startups/__init__.py
guise-0.0.8.dist-info/LICENSE
guise-0.0.8.dist-info/METADATA
guise-0.0.8.dist-info/WHEEL
guise-0.0.8.dist-info/top_level.txt
guise-0.0.8.dist-info/RECORD
